{"state":"KY","total":0,"candidates":
{"60705":"GOP|Barr|Andy Barr","1306":"GOP|Davis|Geoff Davis","202":"GOP|Whitfield|Ed Whitfield","60208":"GOP|Paul|Rand Paul","204":"Dem|Conway|Jack Conway","59743":"Dem|Holbert|Jim Holbert","60704":"Ind|Hansen|Michael Hansen","208":"GOP|Rogers|Hal Rogers","60532":"Dem|Waltz|John Waltz","1310":"Dem|Chandler|Ben Chandler","60703":"Dem|Marksberry|Ed Marksberry","59793":"Lib|Martin|Edward Martin","20552":"GOP|Lally|Todd Lally","54282":"GOP|Guthrie|Brett Guthrie","51522":"Dem|Yarmuth|John Yarmuth","60530":"Dem|Hatchett|Charles Hatchett"},
"locals":
{},
"totals":
{"name":"Kentucky","fix":
{"LaRue":"Larue"},
"precincts":
{"total":515,"reporting":265},
"races":
{"U.S. House":
{"1":
{"votes":[
{"votes":1008,"id":"60530"},
{"votes":1008,"id":"202"}]},
"3":
{"votes":[
{"votes":2702,"id":"51522"},
{"votes":2002,"id":"20552"},
{"votes":525,"id":"60704"},
{"votes":425,"id":"59793"}]},
"2":
{"votes":[
{"votes":2501,"id":"54282"},
{"votes":2325,"id":"60703"}]},
"5":
{"votes":[
{"votes":1203,"id":"208"},
{"votes":1203,"id":"59743"}]},
"4":
{"votes":[
{"votes":5889,"id":"60532"},
{"votes":5743,"id":"1306"}]},
"6":
{"votes":[
{"votes":804,"id":"60705"},
{"votes":804,"id":"1310"}]}},
"U.S. Senate":
{"":
{"votes":[
{"votes":37145,"id":"60208"},
{"votes":35478,"id":"204"}]}}},
"abbr":"KY"}}